tljh_db.py
tljh_db-0.5.dist-info/WHEEL
tljh_db-0.5.dist-info/METADATA
tljh_db-0.5.dist-info/LICENSE
tljh_db-0.5.dist-info/RECORD
