Metadata-Version: 2.1
Name: tljh-db
Version: 0.5
Summary: The littlest jupyterhub plugin for working with mysql databases
License: UNKNOWN
Author-email: Christoph Blessing <33834216+cblessing24@users.noreply.github.com>
Requires-Python: >=3.8
Classifier: Programming Language :: Python :: 3
Classifier: Programming Language :: Python :: 3.8
Classifier: Programming Language :: Python :: 3.9
Requires-Dist: pymysql~=1.0
Requires-Dist: xkcdpass~=1.17
Project-URL: homepage, https://github.com/sinzlab/tljh-db
